django_perm_trans/__init__.py
django_perm_trans/admin.py
django_perm_trans/apps.py
django_perm_trans/exceptions.py
django_perm_trans/functions.py
django_perm_trans/migrations/__init__.py
django_perm_trans/models.py
django_perm_trans/tests.py
django_perm_trans-0.1.1.dist-info/LICENSE.md
django_perm_trans-0.1.1.dist-info/METADATA
django_perm_trans-0.1.1.dist-info/WHEEL
django_perm_trans-0.1.1.dist-info/RECORD
