Metadata-Version: 2.1
Name: django-perm-trans
Version: 0.1.1
Summary: A simple way to translate the permissions of your Django project.
License: MIT
Author: Silas Vasconcelos
Author-email: silasvasconcelos@hotmail.com.br
Requires-Python: >=3.8,<4.0
Classifier: License :: OSI Approved :: MIT License
Classifier: Programming Language :: Python :: 3
Classifier: Programming Language :: Python :: 3.8
Classifier: Programming Language :: Python :: 3.9
Classifier: Programming Language :: Python :: 3.10
Classifier: Programming Language :: Python :: 3.11
Requires-Dist: dotpath (>=0.1.0,<0.2.0)
